unreasonably_long_core/__init__.py
unreasonably_long_core/util.py
xontrib/uhu.py
xontrib_uhu-0.1.3.post0.dist-info/METADATA
xontrib_uhu-0.1.3.post0.dist-info/WHEEL
xontrib_uhu-0.1.3.post0.dist-info/RECORD
