Metadata-Version: 2.1
Name: xontrib-uhu
Version: 0.1.3.post0
Summary: Xonsh command shortener
Home-page: https://github.com/uninstall-your-browser/uhu_util
License: WTFPL
Keywords: xontrib,xonsh
Author: Your Name
Author-email: you@example.com
Requires-Python: >=3.10,<4.0
Classifier: License :: Other/Proprietary License
Classifier: Programming Language :: Python :: 3
Classifier: Programming Language :: Python :: 3.10
Classifier: Programming Language :: Python :: 3.11
Classifier: Programming Language :: Python :: 3.12
Classifier: Programming Language :: Python :: 3.13
Requires-Dist: httpx (>=0.27.2,<0.28.0)
Requires-Dist: rich (>=13.9.3,<14.0.0)
Requires-Dist: xonsh (>=0.18.4,<0.19.0)
Project-URL: Repository, https://github.com/uninstall-your-browser/uhu_util
